datacatalog_fileset_enricher/__init__.py
datacatalog_fileset_enricher/datacatalog_fileset_enricher.py
datacatalog_fileset_enricher/datacatalog_fileset_enricher_cli.py
datacatalog_fileset_enricher/datacatalog_helper.py
datacatalog_fileset_enricher/gcs_storage_client_helper.py
datacatalog_fileset_enricher/gcs_storage_filter.py
datacatalog_fileset_enricher/gcs_storage_stats_summarizer.py
datacatalog_fileset_enricher-1.2.0.dist-info/LICENSE
datacatalog_fileset_enricher-1.2.0.dist-info/METADATA
datacatalog_fileset_enricher-1.2.0.dist-info/WHEEL
datacatalog_fileset_enricher-1.2.0.dist-info/top_level.txt
datacatalog_fileset_enricher-1.2.0.dist-info/RECORD
